[
  {
    "keyword": "Feature",
    "name": "First suite testing support-tools",
    "line": 1,
    "id": "first-suite-testing-support-tools",
    "tags": [],
    "uri": "suiteOne.feature",
    "elements": [
      {
        "id": "first-suite-testing-support-tools;open-page-click-and-validate",
        "keyword": "Scenario",
        "line": 7,
        "name": "Open page click and validate",
        "tags": [
          {
            "name": "@tagOne",
            "line": 6
          },
          {
            "name": "@GeniusBar",
            "line": 6
          },
          {
            "name": "@First",
            "line": 6
          }
        ],
        "type": "scenario",
        "steps": [
          {
            "arguments": [],
            "keyword": "Given ",
            "line": 4,
            "name": "I log in",
            "result": {
              "status": "passed",
              "duration": 16526000000
            }
          },
          {
            "arguments": [],
            "keyword": "Given ",
            "line": 8,
            "name": "I click the submit button",
            "result": {
              "status": "failed",
              "duration": 25115000000,
              "error_message": "AssertionError: Timed out retrying after 25000ms: Expected to find element: `div#postButton>a`, but never found it.\n    at Context.eval (https://support-tools-ui-support-tools-test.apps.dc11-stage-01.cld.omnitracs.com/__cypress/tests?p=cypress\\integration\\suiteOne.feature:75:6)\n    at Context.resolveAndRunStepDefinition (https://support-tools-ui-support-tools-test.apps.dc11-stage-01.cld.omnitracs.com/__cypress/tests?p=cypress\\integration\\suiteOne.feature:10490:29)\n    at Context.eval (https://support-tools-ui-support-tools-test.apps.dc11-stage-01.cld.omnitracs.com/__cypress/tests?p=cypress\\integration\\suiteOne.feature:9835:35)"
            }
          },
          {
            "arguments": [],
            "keyword": "Then ",
            "line": 9,
            "name": "I got an error message",
            "result": {
              "status": "skipped"
            }
          }
        ]
      }
    ]
  }
]